qcrit/__init__.py
qcrit/analyze_models.py
qcrit/color.py
qcrit/extract_features.py
qcrit/model_analyzer.py
qcrit/textual_feature.py
qcrit/analysis/__init__.py
qcrit/analysis/analyzers.py
qcrit/features/__init__.py
qcrit/features/ancient_greek_features.py
qcrit/features/parsed_english_features.py
qcrit/features/universal_features.py
qcrit-0.0.23.dist-info/LICENSE.txt
qcrit-0.0.23.dist-info/METADATA
qcrit-0.0.23.dist-info/WHEEL
qcrit-0.0.23.dist-info/top_level.txt
qcrit-0.0.23.dist-info/RECORD
