Metadata-Version: 2.1
Name: qcrit
Version: 0.0.23
Summary: Easily extract features from texts, and run machine learning algorithms on them. Write your own features, use ours, or do both!
Home-page: https://www.qcrit.org
Author: Tim Gianitsos
Author-email: contact@qcrit.org
License: UNKNOWN
Project-URL: Source Code, https://github.com/QuantitativeCriticismLab/qcrit
Platform: UNKNOWN
Classifier: Programming Language :: Python :: 3.6
Classifier: Programming Language :: Python :: 3.7
Classifier: Programming Language :: Python :: 3.8
Classifier: License :: OSI Approved :: MIT License
Classifier: Operating System :: OS Independent
Requires-Dist: numpy
Requires-Dist: nltk
Requires-Dist: tqdm
